<?xml version="1.0"?>
<directory>
  <file name="stats%20(copia)%20.c" icon_position="263,765"/>
  <file name="handle%20(copia)%20.c" icon_position="118,492"/>
  <file name="death%20(copia)%20.c" icon_position="263,216"/>
  <file name="living.c" icon_position="441,275"/>
  <file name="death.c" icon_position="731,184"/>
  <file name="curses.c" icon_position="586,184"/>
  <file name="alignment.c" icon_position="441,184"/>
  <file name="force.c" icon_position="525,724"/>
  <file name="spells.c" icon_position="436,513"/>
  <file name="wear.c" icon_position="572,182"/>
  <file name="equip.c" icon_position="533,755"/>
</directory>
